{"is_source_file": true, "format": "Python", "description": "Defines the User data model class for the e-commerce backend, including attributes, relationships, and representation method.", "external_files": ["src.models.listing", "src.models.offer", "src.models.swap", "src.models.transaction", "src.models.base"], "external_methods": [], "published": ["User"], "classes": [{"name": "User", "description": "Represents a registered platform user including attributes such as email, username, password, status, and relationships with listings, offers, swaps, and transactions."}], "methods": [{"name": "str __repr__(self)", "description": "Returns a string representation of the User instance for debugging purposes.", "scope": "User", "scopeKind": "class"}], "calls": ["relationship", "mapped_column"], "search-terms": ["User", "SQLAlchemy ORM model", "user.py", "Relationship", "timestamp mixin", "UUID primary key"], "state": 2, "file_id": 12, "knowledge_revision": 64, "git_revision": "", "revision_history": [{"26": ""}, {"64": ""}], "ctags": [{"_type": "tag", "name": "User", "path": "/home/kavia/workspace/code-generation/vintage-market-hub-176149-176159/ecommerce_backend/src/models/user.py", "pattern": "/^class User(Base, UUIDPrimaryKeyMixin, TimestampMixin):$/", "language": "Python", "kind": "class"}, {"_type": "tag", "name": "__repr__", "path": "/home/kavia/workspace/code-generation/vintage-market-hub-176149-176159/ecommerce_backend/src/models/user.py", "pattern": "/^    def __repr__(self) -> str:  # pragma: no cover - debug convenience$/", "language": "Python", "typeref": "typename:str", "kind": "member", "signature": "(self)", "scope": "User", "scopeKind": "class"}, {"_type": "tag", "name": "__tablename__", "path": "/home/kavia/workspace/code-generation/vintage-market-hub-176149-176159/ecommerce_backend/src/models/user.py", "pattern": "/^    __tablename__ = \"users\"$/", "file": true, "language": "Python", "kind": "variable", "scope": "User", "scopeKind": "class"}, {"_type": "tag", "name": "email", "path": "/home/kavia/workspace/code-generation/vintage-market-hub-176149-176159/ecommerce_backend/src/models/user.py", "pattern": "/^    email: Mapped[str] = mapped_column(String(255), unique=True, index=True, nullable=False)$/", "language": "Python", "typeref": "typename:Mapped[str]", "kind": "variable", "scope": "User", "scopeKind": "class"}, {"_type": "tag", "name": "full_name", "path": "/home/kavia/workspace/code-generation/vintage-market-hub-176149-176159/ecommerce_backend/src/models/user.py", "pattern": "/^    full_name: Mapped[Optional[str]] = mapped_column(String(255), default=None)$/", "language": "Python", "typeref": "typename:Mapped[Optional[str]]", "kind": "variable", "scope": "User", "scopeKind": "class"}, {"_type": "tag", "name": "hashed_password", "path": "/home/kavia/workspace/code-generation/vintage-market-hub-176149-176159/ecommerce_backend/src/models/user.py", "pattern": "/^    hashed_password: Mapped[str] = mapped_column(String(255), nullable=False)$/", "language": "Python", "typeref": "typename:Mapped[str]", "kind": "variable", "scope": "User", "scopeKind": "class"}, {"_type": "tag", "name": "is_active", "path": "/home/kavia/workspace/code-generation/vintage-market-hub-176149-176159/ecommerce_backend/src/models/user.py", "pattern": "/^    is_active: Mapped[bool] = mapped_column(Boolean, default=True, nullable=False)$/", "language": "Python", "typeref": "typename:Mapped[bool]", "kind": "variable", "scope": "User", "scopeKind": "class"}, {"_type": "tag", "name": "is_superuser", "path": "/home/kavia/workspace/code-generation/vintage-market-hub-176149-176159/ecommerce_backend/src/models/user.py", "pattern": "/^    is_superuser: Mapped[bool] = mapped_column(Boolean, default=False, nullable=False)$/", "language": "Python", "typeref": "typename:Mapped[bool]", "kind": "variable", "scope": "User", "scopeKind": "class"}, {"_type": "tag", "name": "listings", "path": "/home/kavia/workspace/code-generation/vintage-market-hub-176149-176159/ecommerce_backend/src/models/user.py", "pattern": "/^    listings: Mapped[List[\"Listing\"]] = relationship(back_populates=\"seller\", cascade=\"all, dele/", "language": "Python", "typeref": "typename:Mapped[List[\"Listing\"]]", "kind": "variable", "scope": "User", "scopeKind": "class"}, {"_type": "tag", "name": "offers", "path": "/home/kavia/workspace/code-generation/vintage-market-hub-176149-176159/ecommerce_backend/src/models/user.py", "pattern": "/^    offers: Mapped[List[\"Offer\"]] = relationship(back_populates=\"buyer\", cascade=\"all, delete-or/", "language": "Python", "typeref": "typename:Mapped[List[\"Offer\"]]", "kind": "variable", "scope": "User", "scopeKind": "class"}, {"_type": "tag", "name": "swaps_counterparty", "path": "/home/kavia/workspace/code-generation/vintage-market-hub-176149-176159/ecommerce_backend/src/models/user.py", "pattern": "/^    swaps_counterparty: Mapped[List[\"Swap\"]] = relationship($/", "language": "Python", "typeref": "typename:Mapped[List[\"Swap\"]]", "kind": "variable", "scope": "User", "scopeKind": "class"}, {"_type": "tag", "name": "swaps_initiated", "path": "/home/kavia/workspace/code-generation/vintage-market-hub-176149-176159/ecommerce_backend/src/models/user.py", "pattern": "/^    swaps_initiated: Mapped[List[\"Swap\"]] = relationship($/", "language": "Python", "typeref": "typename:Mapped[List[\"Swap\"]]", "kind": "variable", "scope": "User", "scopeKind": "class"}, {"_type": "tag", "name": "transactions", "path": "/home/kavia/workspace/code-generation/vintage-market-hub-176149-176159/ecommerce_backend/src/models/user.py", "pattern": "/^    transactions: Mapped[List[\"Transaction\"]] = relationship(back_populates=\"buyer\")$/", "language": "Python", "typeref": "typename:Mapped[List[\"Transaction\"]]", "kind": "variable", "scope": "User", "scopeKind": "class"}, {"_type": "tag", "name": "username", "path": "/home/kavia/workspace/code-generation/vintage-market-hub-176149-176159/ecommerce_backend/src/models/user.py", "pattern": "/^    username: Mapped[str] = mapped_column(String(50), unique=True, index=True, nullable=False)$/", "language": "Python", "typeref": "typename:Mapped[str]", "kind": "variable", "scope": "User", "scopeKind": "class"}], "hash": "9ad77dd4bf64019414c6fd7682e8d44d", "format-version": 4, "code-base-name": "ecommerce_backend", "filename": "ecommerce_backend/src/models/user.py", "fields": [{"name": "__tablename__ = \"users\"", "scope": "User", "scopeKind": "class", "description": "unavailable"}, {"name": "Mapped[str] email", "scope": "User", "scopeKind": "class", "description": "unavailable"}, {"name": "Mapped[Optional[str]] full_name", "scope": "User", "scopeKind": "class", "description": "unavailable"}, {"name": "Mapped[str] hashed_password", "scope": "User", "scopeKind": "class", "description": "unavailable"}, {"name": "Mapped[bool] is_active", "scope": "User", "scopeKind": "class", "description": "unavailable"}, {"name": "Mapped[bool] is_superuser", "scope": "User", "scopeKind": "class", "description": "unavailable"}, {"name": "Mapped[List[\"Listing\"]] listings", "scope": "User", "scopeKind": "class", "description": "unavailable"}, {"name": "Mapped[List[\"Offer\"]] offers", "scope": "User", "scopeKind": "class", "description": "unavailable"}, {"name": "Mapped[List[\"Swap\"]] swaps_counterparty", "scope": "User", "scopeKind": "class", "description": "unavailable"}, {"name": "Mapped[List[\"Swap\"]] swaps_initiated", "scope": "User", "scopeKind": "class", "description": "unavailable"}, {"name": "Mapped[List[\"Transaction\"]] transactions", "scope": "User", "scopeKind": "class", "description": "unavailable"}, {"name": "Mapped[str] username", "scope": "User", "scopeKind": "class", "description": "unavailable"}]}