{"is_source_file": true, "format": "Python", "description": "This file defines various Pydantic schema classes for handling category data in an e-commerce backend. It includes base, create, update, and read schemas with validation constraints.", "external_files": ["src.schemas.base"], "external_methods": [], "published": ["CategoryBase", "CategoryCreate", "CategoryUpdate", "CategoryRead"], "classes": [{"name": "CategoryBase", "description": "Base schema with common category fields, extending ORMBase."}, {"name": "CategoryCreate", "description": "Schema for creating a category."}, {"name": "CategoryUpdate", "description": "Schema for updating a category."}, {"name": "CategoryRead", "description": "Schema for reading category data, including id and timestamps."}], "methods": [], "calls": [], "search-terms": ["CategorySchema", "Pydantic", "category", "schema", "ecommerce"], "state": 2, "file_id": 24, "knowledge_revision": 51, "git_revision": "", "ctags": [{"_type": "tag", "name": "CategoryBase", "path": "/home/kavia/workspace/code-generation/vintage-market-hub-176149-176159/ecommerce_backend/src/schemas/category.py", "pattern": "/^class CategoryBase(ORMBase):$/", "language": "Python", "kind": "class"}, {"_type": "tag", "name": "CategoryCreate", "path": "/home/kavia/workspace/code-generation/vintage-market-hub-176149-176159/ecommerce_backend/src/schemas/category.py", "pattern": "/^class CategoryCreate(BaseModel):$/", "language": "Python", "kind": "class"}, {"_type": "tag", "name": "CategoryRead", "path": "/home/kavia/workspace/code-generation/vintage-market-hub-176149-176159/ecommerce_backend/src/schemas/category.py", "pattern": "/^class CategoryRead(CategoryBase):$/", "language": "Python", "kind": "class"}, {"_type": "tag", "name": "CategoryUpdate", "path": "/home/kavia/workspace/code-generation/vintage-market-hub-176149-176159/ecommerce_backend/src/schemas/category.py", "pattern": "/^class CategoryUpdate(BaseModel):$/", "language": "Python", "kind": "class"}, {"_type": "tag", "name": "description", "path": "/home/kavia/workspace/code-generation/vintage-market-hub-176149-176159/ecommerce_backend/src/schemas/category.py", "pattern": "/^    description: Optional[str] = Field(default=None)$/", "language": "Python", "typeref": "typename:Optional[str]", "kind": "variable", "scope": "CategoryBase", "scopeKind": "class"}, {"_type": "tag", "name": "description", "path": "/home/kavia/workspace/code-generation/vintage-market-hub-176149-176159/ecommerce_backend/src/schemas/category.py", "pattern": "/^    description: Optional[str] = None$/", "language": "Python", "typeref": "typename:Optional[str]", "kind": "variable", "scope": "CategoryCreate", "scopeKind": "class"}, {"_type": "tag", "name": "description", "path": "/home/kavia/workspace/code-generation/vintage-market-hub-176149-176159/ecommerce_backend/src/schemas/category.py", "pattern": "/^    description: Optional[str] = None$/", "language": "Python", "typeref": "typename:Optional[str]", "kind": "variable", "scope": "CategoryUpdate", "scopeKind": "class"}, {"_type": "tag", "name": "name", "path": "/home/kavia/workspace/code-generation/vintage-market-hub-176149-176159/ecommerce_backend/src/schemas/category.py", "pattern": "/^    name: Optional[str] = Field(default=None, max_length=120)$/", "language": "Python", "typeref": "typename:Optional[str]", "kind": "variable", "scope": "CategoryUpdate", "scopeKind": "class"}, {"_type": "tag", "name": "name", "path": "/home/kavia/workspace/code-generation/vintage-market-hub-176149-176159/ecommerce_backend/src/schemas/category.py", "pattern": "/^    name: str = Field(..., max_length=120)$/", "language": "Python", "typeref": "typename:str", "kind": "variable", "scope": "CategoryBase", "scopeKind": "class"}, {"_type": "tag", "name": "name", "path": "/home/kavia/workspace/code-generation/vintage-market-hub-176149-176159/ecommerce_backend/src/schemas/category.py", "pattern": "/^    name: str = Field(..., max_length=120)$/", "language": "Python", "typeref": "typename:str", "kind": "variable", "scope": "CategoryCreate", "scopeKind": "class"}], "hash": "b51320de79b28f9f4db085ee45291a74", "format-version": 4, "code-base-name": "ecommerce_backend", "filename": "ecommerce_backend/src/schemas/category.py", "fields": [{"name": "Optional[str] description", "scope": "CategoryBase", "scopeKind": "class", "description": "unavailable"}, {"name": "Optional[str] name", "scope": "CategoryUpdate", "scopeKind": "class", "description": "unavailable"}, {"name": "str name", "scope": "CategoryBase", "scopeKind": "class", "description": "unavailable"}], "revision_history": [{"51": ""}]}